slrdecisionmerger/__init__.py
slrdecisionmerger/__main__.py
slrdecisionmerger/utils/__init__.py
slrdecisionmerger/utils/decision_merger.py
slrdecisionmerger/utils/file_manager.py
slrdecisionmerger/utils/paper_divider.py
slrdecisionmerger-0.1.2.dist-info/licenses/LICENSE
slrdecisionmerger-0.1.2.dist-info/METADATA
slrdecisionmerger-0.1.2.dist-info/WHEEL
slrdecisionmerger-0.1.2.dist-info/entry_points.txt
slrdecisionmerger-0.1.2.dist-info/top_level.txt
slrdecisionmerger-0.1.2.dist-info/RECORD
