Metadata-Version: 2.4
Name: slrdecisionmerger
Version: 0.1.2
Summary: A Python toolkit to divide BibTeX files among reviewers and merge their decisions for Systematic Literature Reviews
Author-email: Rakshit Mittal <pypi@rakshitmittal.net>
License-Expression: MIT
Project-URL: Homepage, https://gitlab.rakshitmittal.net/rmittal/slrdecisionmerger
Requires-Python: >=3.11
License-File: LICENSE
Requires-Dist: bibtexparser~=2.0.0b8
Dynamic: license-file
